evomo/algorithms/__init__.py
evomo/algorithms/hype.py
evomo/algorithms/ibea.py
evomo/algorithms/lmocso.py
evomo/algorithms/moead.py
evomo/algorithms/nsga2.py
evomo/algorithms/nsga3.py
evomo/algorithms/rvea.py
evomo/algorithms/rveaa.py
evomo/algorithms/tensormoead.py
evomo/metrics/__init__.py
evomo/metrics/gd.py
evomo/metrics/hv.py
evomo/metrics/igd.py
evomo/operators/__init__.py
evomo/operators/selection/__init__.py
evomo/operators/selection/non_dominate.py
evomo/operators/selection/rvea_selection.py
evomo/problems/__init__.py
evomo/problems/neuroevolution/__init__.py
evomo/problems/neuroevolution/morobtrol_pro.py
evomo/problems/neuroevolution/morobtrol/__init__.py
evomo/problems/neuroevolution/morobtrol/mo_ant.py
evomo/problems/neuroevolution/morobtrol/mo_half_cheetah.py
evomo/problems/neuroevolution/morobtrol/mo_hopper.py
evomo/problems/neuroevolution/morobtrol/mo_hopper_m3.py
evomo/problems/neuroevolution/morobtrol/mo_humanoid.py
evomo/problems/neuroevolution/morobtrol/mo_humanoidstandup.py
evomo/problems/neuroevolution/morobtrol/mo_inverted_double_pendulum.py
evomo/problems/neuroevolution/morobtrol/mo_pusher.py
evomo/problems/neuroevolution/morobtrol/mo_reacher.py
evomo/problems/neuroevolution/morobtrol/mo_swimmer.py
evomo/problems/neuroevolution/morobtrol/mo_walker2d.py
evomo/problems/numerical/__init__.py
evomo/problems/numerical/dtlz.py
evomo/problems/numerical/lsmop.py
evomo/problems/numerical/maf.py
evomo/problems/numerical/zdt.py
evomo/utils/__init__.py
evomo-0.2.0.dist-info/licenses/LICENSE
evomo-0.2.0.dist-info/METADATA
evomo-0.2.0.dist-info/WHEEL
evomo-0.2.0.dist-info/top_level.txt
evomo-0.2.0.dist-info/RECORD
