Metadata-Version: 2.4
Name: evomo
Version: 0.2.0
Summary: evomo
Author-email: Zhenyu Liang <zhenyuliang97@gmail.com>, Naiwei Yu <yunaiweiyn@gmail.com>, Hao Li <li7526a@gmail.com>, Boqing Xu <xuboqing123@gmail.com>
License:                     GNU GENERAL PUBLIC LICENSE
Project-URL: Homepage, https://github.com/EMI-Group/evomo
Project-URL: Bug Tracker, https://github.com/EMI-Group/evomo/issues
Classifier: Programming Language :: Python :: 3
Classifier: License :: OSI Approved :: GNU General Public License v3 (GPLv3)
Classifier: Intended Audience :: Science/Research
Classifier: Topic :: Scientific/Engineering :: Artificial Intelligence
Requires-Python: >=3.10
License-File: LICENSE
Requires-Dist: torch>=2.6.0
Requires-Dist: evox>=1.2.1
Provides-Extra: vis
Requires-Dist: plotly>=5.0.0; extra == "vis"
Requires-Dist: pandas>=2.0.0; extra == "vis"
Provides-Extra: neuroevolution
Requires-Dist: torchvision>=0.16.0; extra == "neuroevolution"
Requires-Dist: brax>=0.12.0; extra == "neuroevolution"
Provides-Extra: test
Requires-Dist: torchvision>=0.16.0; extra == "test"
Requires-Dist: brax>=0.12.0; extra == "test"
Requires-Dist: plotly>=5.0.0; extra == "test"
Dynamic: license-file
